{
	"orarend": {
		"ora": [
			{
				"targy": "Oracle",
				"idopont": {
					"nap": "Hétfő",
					"tol": "8",
					"ig": "10"
				},
				"helyszin": "Info/103",
				"oktato": "Kovács László",
				"szak": "Mérnök informatika",
				"_id": "01",
				"_tipus": "eloadas"
			},
			{
				"targy": "Oracle",
				"idopont": {
					"nap": "Kedd",
					"tol": "14",
					"ig": "15"
				},
				"helyszin": "Info/202",
				"oktato": "Szűcs Miklós",
				"szak": "Mérnök informatika",
				"_id": "02",
				"_tipus": "gyakorlat"
			},
			{
				"targy": "Webtech1",
				"idopont": {
					"nap": "Hétfő",
					"tol": "10",
					"ig": "12"
				},
				"helyszin": "Eloado 1",
				"oktato": "Agárdi Anita",
				"szak": "Mérnök informatika",
				"_id": "03",
				"_tipus": "eloadas"
			},
			{
				"targy": "Webtech1",
				"idopont": {
					"nap": "Hétfő",
					"tol": "14",
					"ig": "16"
				},
				"helyszin": "Info/101",
				"oktato": "Agárdi Anita",
				"szak": "Mérnök informatika",
				"_id": "04",
				"_tipus": "gyakorlat"
			},
			{
				"targy": "Korszerű tech",
				"idopont": {
					"nap": "Hétfő",
					"tol": "12",
					"ig": "14"
				},
				"helyszin": "Info/103",
				"oktato": "Árvai László",
				"szak": "Mérnök informatika",
				"_id": "05",
				"_tipus": "eloadas"
			},
			{
				"targy": "Korszerű tech",
				"idopont": {
					"nap": "Szerda",
					"tol": "16",
					"ig": "18"
				},
				"helyszin": "Info/15",
				"oktato": "Soós Róbert",
				"szak": "Mérnök informatika",
				"_id": "06",
				"_tipus": "gyakorlat"
			},
			{
				"targy": "WebalkC#",
				"idopont": {
					"nap": "Kedd",
					"tol": "14",
					"ig": "16"
				},
				"helyszin": "Info/101",
				"oktato": "Árvai László",
				"szak": "Mérnök informatika",
				"_id": "07",
				"_tipus": "eloadas"
			},
			{
				"targy": "WebalkC#",
				"idopont": {
					"nap": "Szerda",
					"tol": "16",
					"ig": "18"
				},
				"helyszin": "Info/101",
				"oktato": "Árvai László",
				"szak": "Mérnök informatika",
				"_id": "08",
				"_tipus": "gyakorlat"
			}
		],
		"_xmlns:xs": "http://www.w3.org/2001/XMLSchema-instance",
		"_xs:noNamespaceSchemaLocation": "G0P9OJ_orarend.xsd"
	}
}